[
{"Timestamp":"2026-02-17 00:00:00","ticker":"IWM","dayChange":0.33,"rsi_14":53.6,"EMAs.":"X X O X","ZLEMAs":"X O X","weekRange":92.22},
{"Timestamp":"2026-02-17 00:00:00","ticker":"NVDA","dayChange":1.81,"rsi_14":50.9,"EMAs.":"X X O O","ZLEMAs":"O O X","weekRange":79.23},
{"Timestamp":"2026-02-17 00:00:00","ticker":"DAL","dayChange":3.07,"rsi_14":52.9,"EMAs.":"X X O X","ZLEMAs":"X O O","weekRange":87.34},
{"Timestamp":"2026-02-17 00:00:00","ticker":"BURL","dayChange":2.71,"rsi_14":57.1,"EMAs.":"X X X X","ZLEMAs":"X O X","weekRange":81.87},
{"Timestamp":"2026-02-17 00:00:00","ticker":"HUMA","dayChange":12.87,"rsi_14":55.3,"EMAs.":"O O X X","ZLEMAs":"X X X","weekRange":8.23},
{"Timestamp":"2026-02-17 00:00:00","ticker":"ASML","dayChange":1.35,"rsi_14":60.1,"EMAs.":"X X X X","ZLEMAs":"X O X","weekRange":92.58},
{"Timestamp":"2026-02-17 00:00:00","ticker":"DKS","dayChange":2.8,"rsi_14":50.9,"EMAs.":"O O X X","ZLEMAs":"O X X","weekRange":54.74},
{"Timestamp":"2026-02-17 00:00:00","ticker":"CTAS","dayChange":1.01,"rsi_14":54.3,"EMAs.":"O X O O","ZLEMAs":"O X O","weekRange":30.71},
{"Timestamp":"2026-02-17 00:00:00","ticker":"MU","dayChange":-1.97,"rsi_14":56.9,"EMAs.":"X X X O","ZLEMAs":"X O X","weekRange":86.81},
{"Timestamp":"2026-02-17 00:00:00","ticker":"AAL","dayChange":4.44,"rsi_14":49.5,"EMAs.":"X O O X","ZLEMAs":"X O O","weekRange":74.96},
{"Timestamp":"2026-02-17 00:00:00","ticker":"KLAC","dayChange":0.65,"rsi_14":53.9,"EMAs.":"X X X X","ZLEMAs":"X O X","weekRange":80.77},
{"Timestamp":"2026-02-17 00:00:00","ticker":"ABNB","dayChange":3.34,"rsi_14":47.9,"EMAs.":"O O X X","ZLEMAs":"O O X","weekRange":40.7},
{"Timestamp":"2026-02-17 00:00:00","ticker":"LRCX","dayChange":0.83,"rsi_14":59.7,"EMAs.":"X X X X","ZLEMAs":"X O X","weekRange":92.64},
{"Timestamp":"2026-02-17 00:00:00","ticker":"LULU","dayChange":1.04,"rsi_14":45.5,"EMAs.":"O O O X","ZLEMAs":"X O X","weekRange":8.83},
{"Timestamp":"2026-02-17 00:00:00","ticker":"TMDX","dayChange":5.21,"rsi_14":52.7,"EMAs.":"X O O X","ZLEMAs":"X O X","weekRange":79.36},
{"Timestamp":"2026-02-17 00:00:00","ticker":"DIA","dayChange":0.25,"rsi_14":54.4,"EMAs.":"X X O O","ZLEMAs":"X O O","weekRange":93.68},
{"Timestamp":"2026-02-17 00:00:00","ticker":"TNA","dayChange":0.92,"rsi_14":51.9,"EMAs.":"X X O X","ZLEMAs":"X O O","weekRange":85.93},
{"Timestamp":"2026-02-17 00:00:00","ticker":"SMTC","dayChange":0.83,"rsi_14":60.7,"EMAs.":"X X X X","ZLEMAs":"X X O","weekRange":93.19},
{"Timestamp":"2026-02-17 00:00:00","ticker":"DAVE","dayChange":1.12,"rsi_14":47.1,"EMAs.":"O O X X","ZLEMAs":"O O X","weekRange":51.5},
{"Timestamp":"2026-02-17 00:00:00","ticker":"CAKE","dayChange":5.84,"rsi_14":59.6,"EMAs.":"X X O X","ZLEMAs":"X X X","weekRange":71.84},
{"Timestamp":"2026-02-17 00:00:00","ticker":"PGR","dayChange":1.7,"rsi_14":49.8,"EMAs.":"O O X X","ZLEMAs":"O X X","weekRange":10.61},
{"Timestamp":"2026-02-17 00:00:00","ticker":"ALK","dayChange":4.56,"rsi_14":60.4,"EMAs.":"X X O X","ZLEMAs":"X X O","weekRange":49.83},
{"Timestamp":"2026-02-17 00:00:00","ticker":"LUNA","dayChange":0.0,"rsi_14":65.3,"EMAs.":0,"ZLEMAs":"X X O","weekRange":83.66},
{"Timestamp":"2026-02-17 00:00:00","ticker":"SPOT","dayChange":2.06,"rsi_14":44.5,"EMAs.":"O O X X","ZLEMAs":"O O X","weekRange":16.52},
{"Timestamp":"2026-02-17 00:00:00","ticker":"INSM","dayChange":2.21,"rsi_14":41.6,"EMAs.":"X O O X","ZLEMAs":"O O X","weekRange":60.14},
{"Timestamp":"2026-02-17 00:00:00","ticker":"AVGO","dayChange":2.75,"rsi_14":49.7,"EMAs.":"X O O X","ZLEMAs":"O X X","weekRange":70.89},
{"Timestamp":"2026-02-17 00:00:00","ticker":"DG","dayChange":-2.74,"rsi_14":57.0,"EMAs.":"X X X O","ZLEMAs":"X O O","weekRange":93.68},
{"Timestamp":"2026-02-17 00:00:00","ticker":"CCL","dayChange":3.68,"rsi_14":58.2,"EMAs.":"X X X X","ZLEMAs":"X X O","weekRange":94.25},
{"Timestamp":"2026-02-17 00:00:00","ticker":"PSTG","dayChange":-0.53,"rsi_14":52.8,"EMAs.":"O X X O","ZLEMAs":"O X X","weekRange":58.94},
{"Timestamp":"2026-02-17 00:00:00","ticker":"SOXL","dayChange":1.18,"rsi_14":56.8,"EMAs.":"X X X X","ZLEMAs":"X X X","weekRange":89.77},
{"Timestamp":"2026-02-17 00:00:00","ticker":"SOXX","dayChange":0.39,"rsi_14":58.9,"EMAs.":"X X X X","ZLEMAs":"X X X","weekRange":95.69},
{"Timestamp":"2026-02-17 00:00:00","ticker":"MRVL","dayChange":1.12,"rsi_14":46.8,"EMAs.":"X O O X","ZLEMAs":"O O X","weekRange":49.54},
{"Timestamp":"2026-02-17 00:00:00","ticker":"ROOT","dayChange":5.45,"rsi_14":43.0,"EMAs.":0,"ZLEMAs":"O O X","weekRange":5.03},
{"Timestamp":"2026-02-17 00:00:00","ticker":"UAL","dayChange":4.85,"rsi_14":55.6,"EMAs.":"X X X X","ZLEMAs":"X X X","weekRange":93.13},
{"Timestamp":"2026-02-17 00:00:00","ticker":"WYNN","dayChange":1.05,"rsi_14":49.5,"EMAs.":"X O O X","ZLEMAs":"O X X","weekRange":71.02},
{"Timestamp":"2026-02-13 00:00:00","ticker":"ASPN","dayChange":1.27,"rsi_14":54.5,"EMAs.":"O X X X","ZLEMAs":"X X X","weekRange":11.17},
{"Timestamp":"2026-02-13 00:00:00","ticker":"TSLS","dayChange":1.1,"rsi_14":56.4,"EMAs.":"O X X X","ZLEMAs":"X X X","weekRange":9.51},
{"Timestamp":"2026-02-13 00:00:00","ticker":"STX","dayChange":-1.23,"rsi_14":59.1,"EMAs.":"X X X O","ZLEMAs":"X X O","weekRange":90.14},
{"Timestamp":"2026-02-13 00:00:00","ticker":"ULTA","dayChange":2.47,"rsi_14":63.6,"EMAs.":"X X X X","ZLEMAs":"X X X","weekRange":99.87},
{"Timestamp":"2026-02-13 00:00:00","ticker":"TJX","dayChange":0.54,"rsi_14":54.9,"EMAs.":"X X X X","ZLEMAs":"X O X","weekRange":91.18},
{"Timestamp":"2026-02-13 00:00:00","ticker":"EL","dayChange":2.57,"rsi_14":52.4,"EMAs.":"X O X X","ZLEMAs":"X O X","weekRange":85.51},
{"Timestamp":"2026-02-13 00:00:00","ticker":"MRNA","dayChange":2.6,"rsi_14":56.7,"EMAs.":"X X X X","ZLEMAs":"X O X","weekRange":63.94},
{"Timestamp":"2026-02-13 00:00:00","ticker":"NKE","dayChange":2.12,"rsi_14":53.8,"EMAs.":"O O X X","ZLEMAs":"O X X","weekRange":40.42},
{"Timestamp":"2026-02-13 00:00:00","ticker":"ELF","dayChange":5.28,"rsi_14":54.4,"EMAs.":"O O X X","ZLEMAs":"O X X","weekRange":35.83},
{"Timestamp":"2026-02-13 00:00:00","ticker":"CB","dayChange":2.08,"rsi_14":66.6,"EMAs.":"X X X X","ZLEMAs":"X X O","weekRange":94.62},
{"Timestamp":"2026-02-13 00:00:00","ticker":"ANET","dayChange":1.61,"rsi_14":56.5,"EMAs.":"X X X X","ZLEMAs":"O X X","weekRange":80.03},
{"Timestamp":"2026-02-13 00:00:00","ticker":"UNH","dayChange":-0.8,"rsi_14":43.7,"EMAs.":"O O X X","ZLEMAs":"X O X","weekRange":15.13},
{"Timestamp":"2026-02-13 00:00:00","ticker":"JBLU","dayChange":3.47,"rsi_14":61.7,"EMAs.":"X X X X","ZLEMAs":"X X O","weekRange":61.8},
{"Timestamp":"2026-02-13 00:00:00","ticker":"DXCM","dayChange":1.23,"rsi_14":53.2,"EMAs.":"O O X X","ZLEMAs":"X O X","weekRange":42.85},
{"Timestamp":"2026-02-13 00:00:00","ticker":"PCAR","dayChange":0.15,"rsi_14":60.8,"EMAs.":"X X X X","ZLEMAs":"X O O","weekRange":90.08},
{"Timestamp":"2026-02-12 00:00:00","ticker":"MTDR","dayChange":-1.32,"rsi_14":58.0,"EMAs.":"X X X O","ZLEMAs":"X X O","weekRange":49.85},
{"Timestamp":"2026-02-12 00:00:00","ticker":"CROX","dayChange":3.31,"rsi_14":70.6,"EMAs.":"X X X X","ZLEMAs":"X X X","weekRange":54.17},
{"Timestamp":"2026-02-12 00:00:00","ticker":"TECS","dayChange":-1.16,"rsi_14":54.2,"EMAs.":"O X X X","ZLEMAs":"X X O","weekRange":3.91},
{"Timestamp":"2026-02-12 00:00:00","ticker":"WBD","dayChange":3.33,"rsi_14":63.1,"EMAs.":"X X X X","ZLEMAs":"X O X","weekRange":95.21},
{"Timestamp":"2026-02-12 00:00:00","ticker":"SDS","dayChange":-0.68,"rsi_14":55.6,"EMAs.":"X X X X","ZLEMAs":"O O X","weekRange":87.69},
{"Timestamp":"2026-02-12 00:00:00","ticker":"NBIS","dayChange":-0.42,"rsi_14":54.3,"EMAs.":"X O X X","ZLEMAs":"O X X","weekRange":64.57},
{"Timestamp":"2026-02-12 00:00:00","ticker":"AEO","dayChange":-3.39,"rsi_14":51.0,"EMAs.":"X O X O","ZLEMAs":"X O X","weekRange":79.96},
{"Timestamp":"2026-02-12 00:00:00","ticker":"SPXU","dayChange":-0.98,"rsi_14":54.9,"EMAs.":"X X X X","ZLEMAs":"X O X","weekRange":81.21},
{"Timestamp":"2026-02-12 00:00:00","ticker":"PFGC","dayChange":0.03,"rsi_14":57.9,"EMAs.":"X X X X","ZLEMAs":"O X X","weekRange":72.89},
{"Timestamp":"2026-02-11 00:00:00","ticker":"MIRM","dayChange":0.04,"rsi_14":67.0,"EMAs.":0,"ZLEMAs":"X X X","weekRange":96.22},
{"Timestamp":"2026-02-11 00:00:00","ticker":"QID","dayChange":-0.24,"rsi_14":58.4,"EMAs.":"O X X X","ZLEMAs":"X X X","weekRange":6.87},
{"Timestamp":"2026-02-11 00:00:00","ticker":"COST","dayChange":-0.62,"rsi_14":65.4,"EMAs.":"X X X X","ZLEMAs":"X X X","weekRange":74.09},
{"Timestamp":"2026-02-11 00:00:00","ticker":"F","dayChange":-0.11,"rsi_14":58.9,"EMAs.":"X X X X","ZLEMAs":"X X X","weekRange":93.48},
{"Timestamp":"2026-02-11 00:00:00","ticker":"DLTR","dayChange":1.29,"rsi_14":54.7,"EMAs.":"X O X X","ZLEMAs":"X O X","weekRange":81.74},
{"Timestamp":"2026-02-11 00:00:00","ticker":"SQQQ","dayChange":-0.34,"rsi_14":58.2,"EMAs.":"O X X X","ZLEMAs":"X X X","weekRange":4.73},
{"Timestamp":"2026-02-11 00:00:00","ticker":"WDC","dayChange":1.8,"rsi_14":61.8,"EMAs.":"X X X X","ZLEMAs":"X X O","weekRange":92.51},
{"Timestamp":"2026-02-10 00:00:00","ticker":"VST","dayChange":1.49,"rsi_14":61.3,"EMAs.":"O X X X","ZLEMAs":"O X X","weekRange":64.6},
{"Timestamp":"2026-02-10 00:00:00","ticker":"NET","dayChange":-1.97,"rsi_14":54.6,"EMAs.":"O O X X","ZLEMAs":"O X X","weekRange":60.13},
{"Timestamp":"2026-02-10 00:00:00","ticker":"AMSC","dayChange":7.06,"rsi_14":63.4,"EMAs.":"O X X X","ZLEMAs":"O X X","weekRange":40.17},
{"Timestamp":"2026-02-09 00:00:00","ticker":"TMF","dayChange":0.73,"rsi_14":66.6,"EMAs.":"O X X X","ZLEMAs":"X X X","weekRange":46.58},
{"Timestamp":"2026-02-09 00:00:00","ticker":"ABT","dayChange":-0.33,"rsi_14":44.5,"EMAs.":"O O X O","ZLEMAs":"O O X","weekRange":19.58},
{"Timestamp":"2026-02-06 00:00:00","ticker":"NRG","dayChange":0.97,"rsi_14":68.6,"EMAs.":"X X X X","ZLEMAs":"O X X","weekRange":93.55},
{"Timestamp":"2026-02-06 00:00:00","ticker":"AMAT","dayChange":1.8,"rsi_14":66.3,"EMAs.":"X X X X","ZLEMAs":"X X X","weekRange":94.05},
{"Timestamp":"2026-02-06 00:00:00","ticker":"TSM","dayChange":-0.38,"rsi_14":64.6,"EMAs.":"X X X O","ZLEMAs":"X X O","weekRange":93.88},
{"Timestamp":"2026-02-06 00:00:00","ticker":"DRN","dayChange":2.87,"rsi_14":74.7,"EMAs.":"X X X X","ZLEMAs":"X X X","weekRange":78.7},
{"Timestamp":"2026-02-05 00:00:00","ticker":"GE","dayChange":3.93,"rsi_14":62.5,"EMAs.":"X X X X","ZLEMAs":"O X X","weekRange":97.12},
{"Timestamp":"2026-02-05 00:00:00","ticker":"EME","dayChange":-0.19,"rsi_14":67.9,"EMAs.":"X X X X","ZLEMAs":"X X X","weekRange":93.05},
{"Timestamp":"2026-02-05 00:00:00","ticker":"XLRE","dayChange":0.99,"rsi_14":74.4,"EMAs.":"X X X X","ZLEMAs":"X X X","weekRange":99.88},
{"Timestamp":"2026-02-05 00:00:00","ticker":"ARM","dayChange":1.13,"rsi_14":63.2,"EMAs.":"O X X X","ZLEMAs":"O X X","weekRange":45.27},
{"Timestamp":"2026-02-05 00:00:00","ticker":"TYD","dayChange":-0.03,"rsi_14":67.4,"EMAs.":0,"ZLEMAs":"X X X","weekRange":71.41},
{"Timestamp":"2026-02-05 00:00:00","ticker":"LMT","dayChange":-0.26,"rsi_14":71.0,"EMAs.":"X X X X","ZLEMAs":"X X X","weekRange":97.77},
{"Timestamp":"2026-02-05 00:00:00","ticker":"ROST","dayChange":0.44,"rsi_14":67.9,"EMAs.":"X X X X","ZLEMAs":"X X X","weekRange":97.94},
{"Timestamp":"2026-02-04 00:00:00","ticker":"ROAD","dayChange":1.53,"rsi_14":72.0,"EMAs.":0,"ZLEMAs":"X X X","weekRange":92.32},
{"Timestamp":"2026-02-04 00:00:00","ticker":"PFE","dayChange":-0.6,"rsi_14":60.3,"EMAs.":"X X X O","ZLEMAs":"X X O","weekRange":92.53},
{"Timestamp":"2026-02-04 00:00:00","ticker":"ON","dayChange":-0.64,"rsi_14":70.1,"EMAs.":"X X X X","ZLEMAs":"X X X","weekRange":95.57},
{"Timestamp":"2026-02-04 00:00:00","ticker":"GGLS","dayChange":1.17,"rsi_14":70.5,"EMAs.":0,"ZLEMAs":"X X X","weekRange":9.45},
{"Timestamp":"2026-02-04 00:00:00","ticker":"LNG","dayChange":-0.75,"rsi_14":64.8,"EMAs.":0,"ZLEMAs":"O X O","weekRange":54.68},
{"Timestamp":"2026-02-03 00:00:00","ticker":"WM","dayChange":0.42,"rsi_14":66.4,"EMAs.":"X X X X","ZLEMAs":"X X X","weekRange":85.39},
{"Timestamp":"2026-02-03 00:00:00","ticker":"KMB","dayChange":-1.55,"rsi_14":65.3,"EMAs.":"O X X O","ZLEMAs":"X X O","weekRange":21.14},
{"Timestamp":"2026-02-03 00:00:00","ticker":"GRBK","dayChange":-1.11,"rsi_14":70.4,"EMAs.":0,"ZLEMAs":"X X X","weekRange":95.81},
{"Timestamp":"2026-02-03 00:00:00","ticker":"AMZD","dayChange":-1.08,"rsi_14":74.2,"EMAs.":"X X X O","ZLEMAs":"X X O","weekRange":39.54},
{"Timestamp":"2026-01-30 00:00:00","ticker":"DECK","dayChange":1.15,"rsi_14":63.9,"EMAs.":"X X X X","ZLEMAs":"X X O","weekRange":49.1},
{"Timestamp":"2026-01-30 00:00:00","ticker":"TGT","dayChange":-0.06,"rsi_14":63.0,"EMAs.":"X X X X","ZLEMAs":"X X O","weekRange":66.83},
{"Timestamp":"2026-01-30 00:00:00","ticker":"HLT","dayChange":1.24,"rsi_14":64.4,"EMAs.":"X X X O","ZLEMAs":"X X O","weekRange":88.88},
{"Timestamp":"2026-01-30 00:00:00","ticker":"MRK","dayChange":0.3,"rsi_14":70.0,"EMAs.":"X X X X","ZLEMAs":"X X O","weekRange":96.9},
{"Timestamp":"2026-01-30 00:00:00","ticker":"KYMR","dayChange":2.65,"rsi_14":65.0,"EMAs.":"X X X X","ZLEMAs":"X X X","weekRange":77.88},
{"Timestamp":"2026-01-30 00:00:00","ticker":"WMT","dayChange":-3.96,"rsi_14":59.6,"EMAs.":"X X X O","ZLEMAs":"X X O","weekRange":88.88},
{"Timestamp":"2026-01-29 00:00:00","ticker":"TMUS","dayChange":0.31,"rsi_14":74.2,"EMAs.":"O X X X","ZLEMAs":"X X X","weekRange":40.8},
{"Timestamp":"2026-01-29 00:00:00","ticker":"VZ","dayChange":0.17,"rsi_14":79.3,"EMAs.":"X X X O","ZLEMAs":"X X O","weekRange":97.11},
{"Timestamp":"2026-01-29 00:00:00","ticker":"FNGD","dayChange":-1.24,"rsi_14":68.6,"EMAs.":"O X X X","ZLEMAs":"X X X","weekRange":12.23},
{"Timestamp":"2026-01-29 00:00:00","ticker":"MSFD","dayChange":1.02,"rsi_14":68.3,"EMAs.":"X X X X","ZLEMAs":"X X O","weekRange":58.73},
{"Timestamp":"2026-01-29 00:00:00","ticker":"CMCSA","dayChange":1.05,"rsi_14":65.5,"EMAs.":"O X X O","ZLEMAs":"X X O","weekRange":50.31},
{"Timestamp":"2026-01-28 00:00:00","ticker":"BIIB","dayChange":-0.55,"rsi_14":62.7,"EMAs.":"X X X O","ZLEMAs":"X X O","weekRange":92.45},
{"Timestamp":"2026-01-28 00:00:00","ticker":"T","dayChange":0.23,"rsi_14":80.2,"EMAs.":"X X X X","ZLEMAs":"X X O","weekRange":84.87},
{"Timestamp":"2026-01-27 00:00:00","ticker":"FDX","dayChange":0.48,"rsi_14":83.2,"EMAs.":"X X X X","ZLEMAs":"X X O","weekRange":97.09},
{"Timestamp":"2026-01-26 00:00:00","ticker":"CAT","dayChange":-1.13,"rsi_14":70.3,"EMAs.":"X X X O","ZLEMAs":"X X O","weekRange":95.33},
{"Timestamp":"2026-01-26 00:00:00","ticker":"DAKT","dayChange":0.47,"rsi_14":83.2,"EMAs.":"X X X X","ZLEMAs":"X X X","weekRange":99.14},
{"Timestamp":"2026-01-23 00:00:00","ticker":"MCD","dayChange":-0.41,"rsi_14":61.2,"EMAs.":"X X X O","ZLEMAs":"X X O","weekRange":81.92},
{"Timestamp":"2026-01-21 00:00:00","ticker":"AAP","dayChange":-2.63,"rsi_14":67.2,"EMAs.":"X X X O","ZLEMAs":"X X O","weekRange":69.11},
{"Timestamp":"2026-01-21 00:00:00","ticker":"VNOM","dayChange":-0.81,"rsi_14":68.0,"EMAs.":"X X X X","ZLEMAs":"X X O","weekRange":54.77},
{"Timestamp":"2026-01-21 00:00:00","ticker":"PM","dayChange":-1.97,"rsi_14":63.0,"EMAs.":"X X X O","ZLEMAs":"X X O","weekRange":85.33},
{"Timestamp":"2026-01-12 00:00:00","ticker":"PG","dayChange":-0.36,"rsi_14":67.9,"EMAs.":"X X X O","ZLEMAs":"X X O","weekRange":51.62},
{"Timestamp":"2026-01-08 00:00:00","ticker":"ERX","dayChange":-2.63,"rsi_14":64.8,"EMAs.":"X X X O","ZLEMAs":"X X O","weekRange":88.94},
{"Timestamp":"2026-01-08 00:00:00","ticker":"XLE","dayChange":-1.27,"rsi_14":66.3,"EMAs.":"X X X O","ZLEMAs":"X X O","weekRange":91.22},
{"Timestamp":"2026-01-06 00:00:00","ticker":"ECL","dayChange":1.42,"rsi_14":72.8,"EMAs.":"X X X X","ZLEMAs":"X X X","weekRange":96.34},
{"Timestamp":"2026-01-06 00:00:00","ticker":"DE","dayChange":0.33,"rsi_14":76.2,"EMAs.":"X X X O","ZLEMAs":"X X O","weekRange":90.39},
{"Timestamp":"2026-01-02 00:00:00","ticker":"POWL","dayChange":-3.5,"rsi_14":70.3,"EMAs.":0,"ZLEMAs":"X X O","weekRange":89.73},
{"Timestamp":"2026-01-02 00:00:00","ticker":"TXN","dayChange":0.22,"rsi_14":69.7,"EMAs.":"X X X X","ZLEMAs":"X X O","weekRange":94.9},
{"Timestamp":"2025-07-17 00:00:00","ticker":"HES","dayChange":0.96,"rsi_14":0,"EMAs.":0,"ZLEMAs":0,"weekRange":65.95}
]