[
{"EMAs":"O X X X O O","ticker":"LMT","dayChange":-0.16,"weekRange":25.23},
{"EMAs":"O O X X X X","ticker":"TSLA","dayChange":2.73,"weekRange":44.78},
{"EMAs":"X X O O X X","ticker":"PDD","dayChange":-0.41,"weekRange":25.55},
{"EMAs":"X O O O X O","ticker":"MDB","dayChange":-1.05,"weekRange":28.66},
{"EMAs":"X X X O O O","ticker":"ABNB","dayChange":-0.14,"weekRange":56.94},
{"EMAs":"X X O O X X","ticker":"LLY","dayChange":2.69,"weekRange":39.07},
{"EMAs":"X X X X X O","ticker":"AAPL","dayChange":0.34,"weekRange":44.69},
{"EMAs":"X X O O O X","ticker":"IONQ","dayChange":0.97,"weekRange":73.48},
{"EMAs":"X X O O O O","ticker":"TNA","dayChange":-0.2,"weekRange":41.61},
{"EMAs":"X X X X O O","ticker":"AMZN","dayChange":-1.17,"weekRange":79.31},
{"EMAs":"X X O O O O","ticker":"NKE","dayChange":-0.47,"weekRange":50.52},
{"EMAs":"X X X O O O","ticker":"HLT","dayChange":-0.42,"weekRange":92.5},
{"EMAs":"X X X X X O","ticker":"MSFT","dayChange":-0.3,"weekRange":97.54},
{"EMAs":"X X O O O X","ticker":"XYZ","dayChange":2.06,"weekRange":46.22},
{"EMAs":"X X X O O O","ticker":"UPRO","dayChange":-0.26,"weekRange":86.23},
{"EMAs":"X X X X X X","ticker":"GM","dayChange":0.97,"weekRange":64.0},
{"EMAs":"X X O O O O","ticker":"EL","dayChange":-0.52,"weekRange":67.7},
{"EMAs":"X X X X O O","ticker":"ANF","dayChange":-0.71,"weekRange":21.54},
{"EMAs":"X X X X X X","ticker":"GOOGL","dayChange":0.7,"weekRange":64.24},
{"EMAs":"X X X O O X","ticker":"CAVA","dayChange":0.44,"weekRange":18.14},
{"EMAs":"X X X X X O","ticker":"BURL","dayChange":0.23,"weekRange":46.02},
{"EMAs":"O O X X O O","ticker":"IBKR","dayChange":-1.59,"weekRange":5.09},
{"EMAs":"X X X X O O","ticker":"TQQQ","dayChange":-0.97,"weekRange":83.37},
{"EMAs":"X X X X X X","ticker":"SHOP","dayChange":2.07,"weekRange":85.21},
{"EMAs":"X X X X X X","ticker":"NU","dayChange":0.18,"weekRange":63.84},
{"EMAs":"X X X X X X","ticker":"CAT","dayChange":0.82,"weekRange":93.02},
{"EMAs":"X X X X X X","ticker":"TSM","dayChange":-0.31,"weekRange":98.57},
{"EMAs":"X X O O O O","ticker":"SOUN","dayChange":-0.12,"weekRange":34.92},
{"EMAs":"X X X O O O","ticker":"SOXL","dayChange":-5.55,"weekRange":35.62},
{"EMAs":"X X X X O O","ticker":"SMTC","dayChange":-1.67,"weekRange":41.89},
{"EMAs":"X X X X X X","ticker":"RCL","dayChange":-0.17,"weekRange":97.06},
{"EMAs":"X X X X X X","ticker":"NVDA","dayChange":-0.25,"weekRange":97.52},
{"EMAs":"X X X X X X","ticker":"AMD","dayChange":-0.67,"weekRange":80.02},
{"EMAs":"X X X X X X","ticker":"MARA","dayChange":6.0,"weekRange":49.22},
{"EMAs":"X X X X O O","ticker":"SOFI","dayChange":0.83,"weekRange":95.43}
]