[
{"ticker":"NVDA","dayChange":-6.84,"weekRange":52.6},
{"ticker":"AAPL","dayChange":-0.05,"weekRange":80.85},
{"ticker":"MSFT","dayChange":-0.77,"weekRange":10.07},
{"ticker":"AMZN","dayChange":-2.22,"weekRange":61.56},
{"ticker":"META","dayChange":-0.45,"weekRange":76.81},
{"ticker":"GOOGL","dayChange":-0.73,"weekRange":50.24},
{"ticker":"GOOG","dayChange":-0.83,"weekRange":50.86},
{"ticker":"TSLA","dayChange":-1.39,"weekRange":42.92},
{"ticker":"BRK.B","dayChange":2.27,"weekRange":98.71},
{"ticker":"UNH","dayChange":-1.47,"weekRange":16.27},
{"ticker":"JNJ","dayChange":0.79,"weekRange":86.4},
{"ticker":"XOM","dayChange":1.07,"weekRange":32.72},
{"ticker":"JPM","dayChange":-1.05,"weekRange":81.81},
{"ticker":"V","dayChange":0.54,"weekRange":98.37},
{"ticker":"PG","dayChange":0.77,"weekRange":80.5},
{"ticker":"LLY","dayChange":1.23,"weekRange":84.45},
{"ticker":"MA","dayChange":0.34,"weekRange":97.4},
{"ticker":"AVGO","dayChange":-3.99,"weekRange":54.28},
{"ticker":"HD","dayChange":1.62,"weekRange":63.0},
{"ticker":"CVX","dayChange":1.24,"weekRange":73.25},
{"ticker":"MRK","dayChange":1.84,"weekRange":20.92},
{"ticker":"PEP","dayChange":0.95,"weekRange":28.54},
{"ticker":"ABBV","dayChange":1.96,"weekRange":98.98},
{"ticker":"COST","dayChange":0.8,"weekRange":94.41},
{"ticker":"PFE","dayChange":-1.0,"weekRange":23.87},
{"ticker":"KO","dayChange":0.48,"weekRange":85.13},
{"ticker":"ADBE","dayChange":1.48,"weekRange":22.43},
{"ticker":"CRM","dayChange":-0.15,"weekRange":54.4},
{"ticker":"WMT","dayChange":-0.58,"weekRange":84.51},
{"ticker":"TMO","dayChange":1.1,"weekRange":26.5},
{"ticker":"NEE","dayChange":1.14,"weekRange":50.45},
{"ticker":"MCD","dayChange":-1.42,"weekRange":81.23},
{"ticker":"CSCO","dayChange":0.02,"weekRange":89.2},
{"ticker":"ACN","dayChange":-0.45,"weekRange":57.02},
{"ticker":"ABT","dayChange":1.65,"weekRange":98.65},
{"ticker":"DHR","dayChange":1.0,"weekRange":12.91},
{"ticker":"CMCSA","dayChange":1.38,"weekRange":26.39},
{"ticker":"TXN","dayChange":1.14,"weekRange":63.83},
{"ticker":"PM","dayChange":1.79,"weekRange":99.29},
{"ticker":"VZ","dayChange":1.26,"weekRange":77.94},
{"ticker":"INTC","dayChange":0.7,"weekRange":19.15},
{"ticker":"UNP","dayChange":0.66,"weekRange":71.2},
{"ticker":"BMY","dayChange":1.39,"weekRange":93.2},
{"ticker":"MDT","dayChange":1.41,"weekRange":93.81},
{"ticker":"HON","dayChange":0.29,"weekRange":43.64},
{"ticker":"QCOM","dayChange":-0.36,"weekRange":8.83},
{"ticker":"AMGN","dayChange":0.73,"weekRange":58.54},
{"ticker":"C","dayChange":1.37,"weekRange":84.66},
{"ticker":"CAT","dayChange":-2.2,"weekRange":26.31}
]