[
{"EMAs":"X O O X X X","ticker":"LLY","dayChange":0.88,"rsi_14":55.8,"weekRange":80.81},
{"EMAs":"X X O O O O","ticker":"AVGO","dayChange":-10.86,"rsi_14":44.7,"weekRange":81.06},
{"EMAs":"X X O O O O","ticker":"GOOG","dayChange":-1.11,"rsi_14":55.9,"weekRange":90.08},
{"EMAs":"X X X X X O","ticker":"TSLA","dayChange":-0.53,"rsi_14":54.6,"weekRange":83.95},
{"EMAs":"X X X O O O","ticker":"ASML","dayChange":-3.19,"rsi_14":54.2,"weekRange":90.28},
{"EMAs":"O O O O O O","ticker":"BABA","dayChange":-1.46,"rsi_14":42.7,"weekRange":66.2},
{"EMAs":"O O O O O O","ticker":"PDD","dayChange":-0.87,"rsi_14":26.6,"weekRange":45.68},
{"EMAs":"O O O O X O","ticker":"OLLI","dayChange":0.03,"rsi_14":42.1,"weekRange":45.51},
{"EMAs":"O O O O X X","ticker":"T","dayChange":1.52,"rsi_14":40.1,"weekRange":39.12},
{"EMAs":"O O O O X X","ticker":"NFLX","dayChange":1.12,"rsi_14":32.2,"weekRange":25.06},
{"EMAs":"O O O X X X","ticker":"ABT","dayChange":0.84,"rsi_14":44.7,"weekRange":44.32},
{"EMAs":"O O X X O O","ticker":"WIX","dayChange":0.21,"rsi_14":38.9,"weekRange":6.91},
{"EMAs":"O O X X X X","ticker":"XYZ","dayChange":-0.55,"rsi_14":46.0,"weekRange":38.0},
{"EMAs":"O X X X X X","ticker":"CCL","dayChange":-0.2,"rsi_14":58.9,"weekRange":71.71},
{"EMAs":"X X X O O O","ticker":"KLAC","dayChange":-3.57,"rsi_14":53.6,"weekRange":88.71},
{"EMAs":"X X X X O O","ticker":"PLTR","dayChange":-3.48,"rsi_14":53.7,"weekRange":81.61},
{"EMAs":"X X X X O O","ticker":"SHOP","dayChange":-2.51,"rsi_14":52.4,"weekRange":80.8},
{"EMAs":"X X X X X X","ticker":"DAL","dayChange":0.1,"rsi_14":74.5,"weekRange":97.4},
{"EMAs":"X X X X X X","ticker":"UAL","dayChange":0.13,"rsi_14":64.2,"weekRange":88.34}
]