[
{"EMAs":"O X X X X X","ticker":"GGLS","dayChange":1.22,"rsi_14":46.4,"weekRange":5.4},
{"EMAs":"O O X X X X","ticker":"LABD","dayChange":2.64,"rsi_14":39.7,"weekRange":36.11},
{"EMAs":"O O X X X X","ticker":"TZA","dayChange":2.32,"rsi_14":44.9,"weekRange":3.43},
{"EMAs":"O X X X X X","ticker":"QID","dayChange":0.38,"rsi_14":55.3,"weekRange":5.75},
{"EMAs":"O O X X X X","ticker":"SOXS","dayChange":3.13,"rsi_14":49.3,"weekRange":1.27},
{"EMAs":"O X X X X X","ticker":"SQQQ","dayChange":0.53,"rsi_14":54.8,"weekRange":3.8},
{"EMAs":"O X X X X X","ticker":"TECS","dayChange":0.33,"rsi_14":55.1,"weekRange":3.89},
{"EMAs":"O X X X X X","ticker":"ERY","dayChange":5.58,"rsi_14":60.0,"weekRange":18.93}
]